MANIFEST.in
requirements.txt
setup.cfg
setup.py
mediachain/__init__.py
mediachain/cli/__init__.py
mediachain/cli/main.py
mediachain/datastore/__init__.py
mediachain/datastore/data_objects.py
mediachain/datastore/ipfs.py
mediachain/datastore/rpc.py
mediachain/datastore/utils.py
mediachain/ingestion/__init__.py
mediachain/ingestion/asset_loader.py
mediachain/ingestion/dataset_iterator.py
mediachain/ingestion/directory_iterator.py
mediachain/proto/__init__.py
mediachain/reader/__init__.py
mediachain/reader/api.py
mediachain/reader/utils.py
mediachain/rpc/__init__.py
mediachain/rpc/utils.py
mediachain/transactor/__init__.py
mediachain/transactor/block_cache.py
mediachain/transactor/blockchain_follower.py
mediachain/transactor/client.py
mediachain/translation/__init__.py
mediachain/translation/lookup.py
mediachain/translation/schema.json
mediachain/translation/translator.py
mediachain/translation/utils.py
mediachain/utils/__init__.py
mediachain/utils/file.py
mediachain/utils/log.py
mediachain/writer/__init__.py
mediachain/writer/writer.py
mediachain_client.egg-info/PKG-INFO
mediachain_client.egg-info/SOURCES.txt
mediachain_client.egg-info/dependency_links.txt
mediachain_client.egg-info/entry_points.txt
mediachain_client.egg-info/pbr.json
mediachain_client.egg-info/requires.txt
mediachain_client.egg-info/top_level.txt
multihash/__init__.py
multihash/multihash.py
protobuf/Datastore.proto
protobuf/Transactor.proto
protobuf/Types.proto
scripts/build_grpc.sh
scripts/ingest-parallel.py
scripts/install_pyrocksdb.sh
scripts/update_grpcs.sh