Metadata-Version: 1.0
Name: mediachain-client
Version: 0.1.12
Summary: mediachain reader command line interface
Home-page: http://mediachain.io
Author: Mediachain Labs
Author-email: hello@mediachainlabs.com
License: UNKNOWN
Platform: UNKNOWN
